superscraper/__init__.py
superscraper/driver_options.py
superscraper/superscraper.py
superscraper-0.3.11.dist-info/METADATA
superscraper-0.3.11.dist-info/WHEEL
superscraper-0.3.11.dist-info/RECORD
