Metadata-Version: 2.1
Name: superscraper
Version: 0.3.11
Summary: the friendliest scraper around
Author: Mbeebe
Author-email: pyn-sol@beebe.dev
Requires-Python: >=3.8,<4.0
Classifier: Programming Language :: Python :: 3
Classifier: Programming Language :: Python :: 3.8
Classifier: Programming Language :: Python :: 3.9
Classifier: Programming Language :: Python :: 3.10
Classifier: Programming Language :: Python :: 3.11
Requires-Dist: beautifulsoup4 (>=4.11.1,<5.0.0)
Requires-Dist: selenium (>=4.2.0,<5.0.0)
Requires-Dist: webdriver-manager (>=3.7.0,<4.0.0)
